{
  "$schema": "https://mintlify.com/docs.json",
  "theme": "willow",
  "name": "Lemrock Documentation",
  "colors": {
    "primary": "#16A34A",
    "light": "#07C983",
    "dark": "#15803D"
  },
  "favicon": "/favicon.svg",
  "navigation": {
    "tabs": [
      {
        "tab": "Documentation",
        "groups": [
          {
            "group": "Getting Started",
            "pages": ["index", "setup"]
          },
          {
            "group": "Product Data",
            "pages": [
              "integration/product-data-google-merchant-center",
              "integration/product-data-https-push"
            ]
          },
          {
            "group": "Customer Data",
            "pages": [
              "integration/customer-data-webhook",
              "integration/customer-data-mediarithmics",
              "integration/customer-data-salesforce"
            ]
          },
          {
            "group": "Retail Media",
            "pages": [
              "integration/retail-media-criteo",
              "integration/retail-media-mirakl"
            ]
          }
        ]
      }
    ]
  },
  "logo": {
    "light": "/logo/light.png",
    "dark": "/logo/dark.png"
  },
  "navbar": {
    "links": [
      {
        "label": "Support",
        "href": "mailto:contact@lemrock.com"
      }
    ],
    "primary": {
      "type": "button",
      "label": "Console",
      "href": "https://console.lemrock.com"
    }
  },
  "footer": {
    "socials": {
      "linkedin": "https://linkedin.com/company/lemrock"
    }
  }
}
